Phasor/__init__.py
Phasor/src/__init__.py
Phasor/src/conversions.py
Phasor/src/phasor.py
Phasor/src/plot.py
Phasor/src/sc.py
Phasor/tests/__init__.py
Phasor/tests/test_phasor.py
PhasorMath-0.0.2.dist-info/LICENSE
PhasorMath-0.0.2.dist-info/METADATA
PhasorMath-0.0.2.dist-info/WHEEL
PhasorMath-0.0.2.dist-info/top_level.txt
PhasorMath-0.0.2.dist-info/RECORD
