Metadata-Version: 2.1
Name: PhasorMath
Version: 0.0.2
Summary: A basic python package for phasor calculation and phasor represention
Home-page: UNKNOWN
Author: Hansana Prabashwara
License: MIT
Platform: UNKNOWN
Requires-Python: >=3.8
Requires-Dist: numpy
Requires-Dist: plotly
Requires-Dist: pandas
